HISTORY.rst
LICENSE
MANIFEST.in
README.rst
setup.py
ec2stack/__init__.py
ec2stack/__main__.py
ec2stack/configure.py
ec2stack/core.py
ec2stack/errors.py
ec2stack/helpers.py
ec2stack/secretkey_manager.py
ec2stack/services.py
ec2stack.egg-info/PKG-INFO
ec2stack.egg-info/SOURCES.txt
ec2stack.egg-info/dependency_links.txt
ec2stack.egg-info/entry_points.txt
ec2stack.egg-info/not-zip-safe
ec2stack.egg-info/requires.txt
ec2stack.egg-info/top_level.txt
ec2stack/controllers/__init__.py
ec2stack/controllers/default.py
ec2stack/models/__init__.py
ec2stack/models/users/__init__.py
ec2stack/models/users/models.py
ec2stack/providers/__init__.py
ec2stack/providers/cloudstack/__init__.py
ec2stack/providers/cloudstack/disk_offerings.py
ec2stack/providers/cloudstack/images.py
ec2stack/providers/cloudstack/instances.py
ec2stack/providers/cloudstack/keypairs.py
ec2stack/providers/cloudstack/passwords.py
ec2stack/providers/cloudstack/requester.py
ec2stack/providers/cloudstack/security_groups.py
ec2stack/providers/cloudstack/service_offerings.py
ec2stack/providers/cloudstack/snapshots.py
ec2stack/providers/cloudstack/tags.py
ec2stack/providers/cloudstack/volumes.py
ec2stack/providers/cloudstack/vpcs.py
ec2stack/providers/cloudstack/zones.py
ec2stack/templates/change_instance_state.xml
ec2stack/templates/create_keypair.xml
ec2stack/templates/create_security_group.xml
ec2stack/templates/create_volume.xml
ec2stack/templates/generic_error.xml
ec2stack/templates/image_attribute.xml
ec2stack/templates/images.xml
ec2stack/templates/instance_attribute.xml
ec2stack/templates/instances.xml
ec2stack/templates/keypairs.xml
ec2stack/templates/password.xml
ec2stack/templates/response.xml
ec2stack/templates/run_instance.xml
ec2stack/templates/secretkey.xml
ec2stack/templates/securitygroups.xml
ec2stack/templates/status.xml
ec2stack/templates/volume_attachment.xml
ec2stack/templates/volumes.xml
ec2stack/templates/zones.xml
migrations/alembic.ini
migrations/env.py
migrations/versions/1b1a5f6b42a_.py
tests/__init__.py
tests/controller_tests.py
tests/disk_offering_tests.py
tests/factories.py
tests/images_tests.py
tests/instances_tests.py
tests/keypair_tests.py
tests/password_tests.py
tests/security_group_tests.py
