Metadata-Version: 1.1
Name: ec2stack
Version: 0.7.1
Summary: EC2 compatibility interface for Apache Cloudstack
Home-page: http://github.com/imduffy15/ec2stack
Author: Darren Brogan, Ian Duffy
Author-email: brogand2@mail.dcu.ie, duffyi3@mail.dcu.ie
License: Apache License (2.0)
Platform: UNKNOWN
Classifier: Development Status :: 3 - Alpha
Classifier: Environment :: Console
Classifier: Intended Audience :: System Administrators
Classifier: License :: OSI Approved :: Apache Software License
Classifier: Operating System :: OS Independent
Classifier: Programming Language :: Python
Classifier: Topic :: Utilities
Classifier: Programming Language :: Python :: 2.7
